zscore_rs-0.1.1.dist-info/METADATA
zscore_rs-0.1.1.dist-info/WHEEL
zscore_rs-0.1.1.dist-info/licenses/LICENSE
zscore_rs/__init__.py
zscore_rs/zscore_rs.abi3.so
zscore_rs-0.1.1.dist-info/RECORD
