Metadata-Version: 2.4
Name: zscore_rs
Version: 0.1.1
Classifier: Development Status :: 4 - Beta
Classifier: Intended Audience :: Science/Research
Classifier: License :: OSI Approved :: MIT License
Classifier: Programming Language :: Python :: 3
Classifier: Programming Language :: Python :: 3.8
Classifier: Programming Language :: Python :: 3.9
Classifier: Programming Language :: Python :: 3.10
Classifier: Programming Language :: Python :: 3.11
Classifier: Programming Language :: Python :: 3.12
Classifier: Programming Language :: Rust
Classifier: Topic :: Scientific/Engineering
License-File: LICENSE
Summary: Fast Z-score outlier detection implemented in Rust
Keywords: outlier-detection,zscore,statistics,time-series
Author-email: Thomas Q <thomasqsa@gmail.com>
License: MIT
Requires-Python: >=3.8
